assignment-03/demux1x16/demux1x16.v
module demux1x16 (
  output reg [15:0] out,
  input in,
  input [3:0] sel
);
  always @(in, sel) update();

  task update ();
    begin
      out = 16'b0;
      out[sel] = in;
    end
  endtask
endmodule

assignment-03/demux1x16/demux1x16_tb.v
`timescale 1ns/1ps

module demux1x16_tb;
  reg in;
  reg [3:0] sel;
  wire [15:0] out;

  demux1x16 u1(.out(out), .in(in), .sel(sel));

  initial begin
    $dumpfile("demux1x16.vcd");
    $dumpvars;

    in = 1'b1;
    for (integer i = 0; i < 16; i = i + 1) begin
      sel = i; #1;
    end
    
    $finish();
  end
endmodule

assignment-03/demux1x16/demux1x16.vcd
$date
	Sat Jun 13 19:13:42 2026
$end
$version
	Icarus Verilog
$end
$timescale
	1ps
$end
$scope module demux1x16_tb $end
$var wire 16 ! out [15:0] $end
$var reg 1 " in $end
$var reg 4 # sel [3:0] $end
$scope module u1 $end
$var wire 1 " in $end
$var wire 4 $ sel [3:0] $end
$var reg 16 % out [15:0] $end
$scope task update $end
$upscope $end
$upscope $end
$scope begin $ivl_for_loop0 $end
$var integer 32 & i [31:0] $end
$upscope $end
$upscope $end
$enddefinitions $end
$comment Show the parameter values. $end
$dumpall
$end
#0
$dumpvars
b0 &
b1 %
b0 $
b0 #
1"
b1 !
$end
#1000
b10 !
b10 %
b1 #
b1 $
b1 &
#2000
b100 !
b100 %
b10 #
b10 $
b10 &
#3000
b1000 !
b1000 %
b11 #
b11 $
b11 &
#4000
b10000 !
b10000 %
b100 #
b100 $
b100 &
#5000
b100000 !
b100000 %
b101 #
b101 $
b101 &
#6000
b1000000 !
b1000000 %
b110 #
b110 $
b110 &
#7000
b10000000 !
b10000000 %
b111 #
b111 $
b111 &
#8000
b100000000 !
b100000000 %
b1000 #
b1000 $
b1000 &
#9000
b1000000000 !
b1000000000 %
b1001 #
b1001 $
b1001 &
#10000
b10000000000 !
b10000000000 %
b1010 #
b1010 $
b1010 &
#11000
b100000000000 !
b100000000000 %
b1011 #
b1011 $
b1011 &
#12000
b1000000000000 !
b1000000000000 %
b1100 #
b1100 $
b1100 &
#13000
b10000000000000 !
b10000000000000 %
b1101 #
b1101 $
b1101 &
#14000
b100000000000000 !
b100000000000000 %
b1110 #
b1110 $
b1110 &
#15000
b1000000000000000 !
b1000000000000000 %
b1111 #
b1111 $
b1111 &
#16000
b10000 &
