assignment-03/decoder3x8/decoder3x8.v
module decoder3x8 (
  output reg [7:0] out,
  input [2:0] in
);
  always @(in) update();

  task update ();
    begin
      out = 8'b1 << in;
    end
  endtask
endmodule

assignment-03/decoder3x8/decoder3x8_tb.v
`timescale 1ns/1ps

module decoder3x8_tb;
  reg [2:0] in;
  wire [7:0] out;

  decoder3x8 u1(.out(out), .in(in));

  initial begin
    $dumpfile("decoder3x8.vcd");
    $dumpvars;
    
    for (integer i = 0; i < 8; i = i + 1) begin
      in = i; #1;
    end

    $finish;
  end
endmodule

assignment-03/decoder3x8/decoder3x8.vcd
$date
	Sat Jun 13 19:00:11 2026
$end
$version
	Icarus Verilog
$end
$timescale
	1ps
$end
$scope module decoder3x8_tb $end
$var wire 8 ! out [7:0] $end
$var reg 3 " in [2:0] $end
$scope module u1 $end
$var wire 3 # in [2:0] $end
$var reg 8 $ out [7:0] $end
$scope task update $end
$upscope $end
$upscope $end
$scope begin $ivl_for_loop0 $end
$var integer 32 % i [31:0] $end
$upscope $end
$upscope $end
$enddefinitions $end
$comment Show the parameter values. $end
$dumpall
$end
#0
$dumpvars
b0 %
b1 $
b0 #
b0 "
b1 !
$end
#1000
b10 !
b10 $
b1 "
b1 #
b1 %
#2000
b100 !
b100 $
b10 "
b10 #
b10 %
#3000
b1000 !
b1000 $
b11 "
b11 #
b11 %
#4000
b10000 !
b10000 $
b100 "
b100 #
b100 %
#5000
b100000 !
b100000 $
b101 "
b101 #
b101 %
#6000
b1000000 !
b1000000 $
b110 "
b110 #
b110 %
#7000
b10000000 !
b10000000 $
b111 "
b111 #
b111 %
#8000
b1000 %
