assignment-05/async-up-down-counter/design.v
module tff (
  input clk, t,
  input reset,                //active-low
  output reg q
);
  //+ve edge trigerred, asynchronous active-low preset
  always @(posedge clk or negedge reset)
    if (!reset)
      q <= 1'b0;
    else
      if (t)
        q <= ~q;
endmodule

module async_up_down_counter #(
  parameter N = 8
) (
  input clk,
  input countDown,            //if 1'b0 count up otherwise down
  input reset,                //active-low
  output [N-1:0] value
);
  wire [N-1:1] aux_clk;
  //If the "clk" input of next FF is connected to output "q" of previous FF, resultant is Down counter
  //If the "clk" input of next FF is connected to output "qbar" of previous FF, resultant is Up counter
  assign aux_clk = (countDown)? value[N-2:0] : ~value[N-2:0];

  tff first(.clk(clk), .t(1'b1), .reset(reset), .q(value[0]));

  genvar p;
  generate
    for (p = 1; p < N; p = p + 1) begin : g1
      tff ff(.clk(aux_clk[p]), .t(1'b1), .reset(reset), .q(value[p]));
    end
  endgenerate
endmodule

assignment-05/async-up-down-counter/tb.v
`timescale 1ns/100ps

module async_up_down_counter_tb;
  reg clk, countDown, reset;
  wire [1:0] value;

  async_up_down_counter#(2) u(.clk(clk), .reset(reset), .countDown(countDown), .value(value));

  initial begin
    clk = 1'b0;
    countDown = 1'b0;      //count up
    forever #5 clk = ~clk; //100 MHz frequency 
  end

  initial begin
    $dumpfile("waveforms.vcd");
    $dumpvars(0, async_up_down_counter_tb);
    
    //resetting te FF
    #1 reset = 1'b0;
    #1 reset = 1'b1;

    //One clock cycle elapsed

    #60 countDown = 1'b1;
    #60 countDown = 1'b0;

    #4 $finish;
  end
endmodule

assignment-05/async-up-down-counter/waveforms.vcd
$date
	Tue Jun 23 11:33:12 2026
$end
$version
	Icarus Verilog
$end
$timescale
	100ps
$end
$scope module async_up_down_counter_tb $end
$var wire 2 ! value [1:0] $end
$var reg 1 " clk $end
$var reg 1 # countDown $end
$var reg 1 $ reset $end
$scope module u $end
$var wire 1 " clk $end
$var wire 1 # countDown $end
$var wire 1 $ reset $end
$var wire 2 % value [1:0] $end
$var wire 1 & aux_clk [1:1] $end
$var parameter 32 ' N $end
$scope begin g1[1] $end
$var parameter 2 ( p $end
$scope module ff $end
$var wire 1 & clk $end
$var wire 1 $ reset $end
$var wire 1 ) t $end
$var reg 1 * q $end
$upscope $end
$upscope $end
$scope module first $end
$var wire 1 " clk $end
$var wire 1 $ reset $end
$var wire 1 + t $end
$var reg 1 , q $end
$upscope $end
$upscope $end
$upscope $end
$enddefinitions $end
$comment Show the parameter values. $end
$dumpall
b1 (
b10 '
$end
#0
$dumpvars
x,
1+
x*
1)
x&
bx %
x$
0#
0"
bx !
$end
#10
1&
b0 !
b0 %
0,
0*
0$
#20
1$
#50
0&
b1 !
b1 %
1,
1"
#100
0"
#150
1*
1&
b10 !
b10 %
0,
1"
#200
0"
#250
0&
b11 !
b11 %
1,
1"
#300
0"
#350
0*
1&
b0 !
b0 %
0,
1"
#400
0"
#450
0&
b1 !
b1 %
1,
1"
#500
0"
#550
1*
1&
b10 !
b10 %
0,
1"
#600
0"
#620
0&
1#
#650
0*
1&
b1 !
b1 %
1,
1"
#700
0"
#750
0&
b0 !
b0 %
0,
1"
#800
0"
#850
1*
1&
b11 !
b11 %
1,
1"
#900
0"
#950
0&
b10 !
b10 %
0,
1"
#1000
0"
#1050
0*
1&
b1 !
b1 %
1,
1"
#1100
0"
#1150
0&
b0 !
b0 %
0,
1"
#1200
0"
#1220
b10 !
b10 %
1*
1&
0#
#1250
0&
b11 !
b11 %
1,
1"
