assignment-01/four_bit_ripple_carry_adder/four_bit_ripple_carry_adder.v
//Dataflow modelling
module four_bit_ripple_carry_adder_df(
  output [3:0] Sum,
  output Cout,
  input [3:0] A, B,
  input Cin
);
  assign {Cout, Sum} = A + B + Cin;
endmodule

//Behavioral Modelling
module four_bit_ripple_carry_adder_beh(
  output reg [3:0] Sum,
  output reg Cout,
  input [3:0] A, B,
  input Cin
);
  always @(*) begin
    {Cout, Sum} = A + B + Cin;
  end
endmodule


module FA(
  output S, C,
  input wire x, y, z
);
  assign S = x ^ y ^ z;
  assign C = (x & y) | (y & z) | (x & z);
endmodule

// Structural Modelling
module four_bit_ripple_carry_adder_st(
  output [3:0] Sum,
  output Cout,
  input [3:0] A, B,
  input Cin
);
  wire w1, w2, w3;
  FA g1(.S(Sum[0]), .C(w1), .x(A[0]), .y(B[0]), .z(Cin));
  FA g2(.S(Sum[1]), .C(w2), .x(A[1]), .y(B[1]), .z(w1));
  FA g3(.S(Sum[2]), .C(w3), .x(A[2]), .y(B[2]), .z(w2));
  FA g4(.S(Sum[3]), .C(Cout), .x(A[3]), .y(B[3]), .z(w3));
endmodule

assignment-01/four_bit_ripple_carry_adder/four_bit_ripple_carry_adder_tb.v
module four_bit_ripple_carry_adder_tb;
  reg [3:0] a, b;
  reg cin;
  wire [3:0] sum_df, sum_beh, sum_st;
  wire cout_df, cout_beh, cout_st;
  
  four_bit_ripple_carry_adder_df u1(.Sum(sum_df), .Cout(cout_df), .A(a), .B(b), .Cin(cin));
  four_bit_ripple_carry_adder_beh u2(.Sum(sum_beh), .Cout(cout_beh), .A(a), .B(b), .Cin(cin));
  four_bit_ripple_carry_adder_st u3(.Sum(sum_st), .Cout(cout_st), .A(a), .B(b), .Cin(cin));

  initial begin
    $dumpfile("four_bit_ripple_carry_adder.vcd");
    $dumpvars(0, four_bit_ripple_carry_adder_tb);
    
       {a, b, cin} = {4'b0000, 4'b0000, 1'b0};
    #1 {a, b, cin} = {4'b0001, 4'b0001, 1'b0};
    #1 {a, b, cin} = {4'b0010, 4'b0001, 1'b0};
    #1 {a, b, cin} = {4'b0101, 4'b0010, 1'b0};
    #1 {a, b, cin} = {4'b0101, 4'b1001, 1'b0};
    #1 {a, b, cin} = {4'b1001, 4'b1101, 1'b0};
    #1 {a, b, cin} = {4'b1001, 4'b1110, 1'b0};
    #1 {a, b, cin} = {4'b0000, 4'b0000, 1'b1};
    #1 {a, b, cin} = {4'b0001, 4'b0001, 1'b1};
    #1 {a, b, cin} = {4'b0010, 4'b0001, 1'b1};
    #1 {a, b, cin} = {4'b0101, 4'b0010, 1'b1};
    #1 {a, b, cin} = {4'b0101, 4'b1001, 1'b1};
    #1 {a, b, cin} = {4'b1001, 4'b1101, 1'b1};
    #1 {a, b, cin} = {4'b1001, 4'b1110, 1'b1};
    #1 $finish;
  end
endmodule

assignment-01/four_bit_ripple_carry_adder/four_bit_ripple_carry_adder.vcd
$date
	Wed May 27 10:21:24 2026
$end
$version
	Icarus Verilog
$end
$timescale
	1s
$end
$scope module four_bit_ripple_carry_adder_tb $end
$var wire 4 ! sum_st [3:0] $end
$var wire 4 " sum_df [3:0] $end
$var wire 4 # sum_beh [3:0] $end
$var wire 1 $ cout_st $end
$var wire 1 % cout_df $end
$var wire 1 & cout_beh $end
$var reg 4 ' a [3:0] $end
$var reg 4 ( b [3:0] $end
$var reg 1 ) cin $end
$scope module u1 $end
$var wire 4 * A [3:0] $end
$var wire 4 + B [3:0] $end
$var wire 1 ) Cin $end
$var wire 4 , Sum [3:0] $end
$var wire 1 % Cout $end
$upscope $end
$scope module u2 $end
$var wire 4 - A [3:0] $end
$var wire 4 . B [3:0] $end
$var wire 1 ) Cin $end
$var reg 1 & Cout $end
$var reg 4 / Sum [3:0] $end
$upscope $end
$scope module u3 $end
$var wire 4 0 A [3:0] $end
$var wire 4 1 B [3:0] $end
$var wire 1 ) Cin $end
$var wire 1 2 w3 $end
$var wire 1 3 w2 $end
$var wire 1 4 w1 $end
$var wire 4 5 Sum [3:0] $end
$var wire 1 $ Cout $end
$scope module g1 $end
$var wire 1 4 C $end
$var wire 1 6 S $end
$var wire 1 7 x $end
$var wire 1 8 y $end
$var wire 1 ) z $end
$upscope $end
$scope module g2 $end
$var wire 1 3 C $end
$var wire 1 9 S $end
$var wire 1 : x $end
$var wire 1 ; y $end
$var wire 1 4 z $end
$upscope $end
$scope module g3 $end
$var wire 1 2 C $end
$var wire 1 < S $end
$var wire 1 = x $end
$var wire 1 > y $end
$var wire 1 3 z $end
$upscope $end
$scope module g4 $end
$var wire 1 $ C $end
$var wire 1 ? S $end
$var wire 1 @ x $end
$var wire 1 A y $end
$var wire 1 2 z $end
$upscope $end
$upscope $end
$upscope $end
$enddefinitions $end
$comment Show the parameter values. $end
$dumpall
$end
#0
$dumpvars
0A
0@
0?
0>
0=
0<
0;
0:
09
08
07
06
b0 5
04
03
02
b0 1
b0 0
b0 /
b0 .
b0 -
b0 ,
b0 +
b0 *
0)
b0 (
b0 '
0&
0%
0$
b0 #
b0 "
b0 !
$end
#1
b10 !
b10 5
19
14
b10 "
b10 ,
17
b10 #
b10 /
18
b1 '
b1 *
b1 -
b1 0
b1 (
b1 +
b1 .
b1 1
#2
04
b11 !
b11 5
0<
16
19
03
b11 "
b11 ,
b11 #
b11 /
07
1:
b10 '
b10 *
b10 -
b10 0
#3
b111 !
b111 5
1<
b111 "
b111 ,
17
0:
1=
b111 #
b111 /
08
1;
b101 '
b101 *
b101 -
b101 0
b10 (
b10 +
b10 .
b10 1
#4
14
b1110 !
b1110 5
06
19
1?
b1110 "
b1110 ,
b1110 #
b1110 /
18
0;
1A
b1001 (
b1001 +
b1001 .
b1001 1
#5
b110 !
b110 5
1$
0?
b110 "
b110 ,
1%
0=
1@
1&
b110 #
b110 /
1>
b1001 '
b1001 *
b1001 -
b1001 0
b1101 (
b1101 +
b1101 .
b1101 1
#6
0?
02
1<
04
b111 !
b111 5
03
16
19
b111 "
b111 ,
b111 #
b111 /
08
1;
b1110 (
b1110 +
b1110 .
b1110 1
#7
09
0$
0<
0%
b1 "
b1 ,
b1 !
b1 5
04
07
0@
0;
0>
0A
0&
b1 #
b1 /
16
b0 '
b0 *
b0 -
b0 0
b0 (
b0 +
b0 .
b0 1
1)
#8
b11 !
b11 5
19
14
b11 "
b11 ,
17
b11 #
b11 /
18
b1 '
b1 *
b1 -
b1 0
b1 (
b1 +
b1 .
b1 1
#9
b100 !
b100 5
1<
06
09
13
b100 "
b100 ,
b100 #
b100 /
07
1:
b10 '
b10 *
b10 -
b10 0
#10
b1000 !
b1000 5
1?
0<
12
b1000 "
b1000 ,
17
0:
1=
b1000 #
b1000 /
08
1;
b101 '
b101 *
b101 -
b101 0
b10 (
b10 +
b10 .
b10 1
#11
02
1<
03
b1111 !
b1111 5
0$
16
19
1?
b1111 "
b1111 ,
b1111 #
b1111 /
18
0;
1A
b1001 (
b1001 +
b1001 .
b1001 1
#12
b111 !
b111 5
1$
0?
b111 "
b111 ,
1%
0=
1@
1&
b111 #
b111 /
1>
b1001 '
b1001 *
b1001 -
b1001 0
b1101 (
b1101 +
b1101 .
b1101 1
#13
1?
12
0<
b1000 !
b1000 5
13
06
09
b1000 "
b1000 ,
b1000 #
b1000 /
08
1;
b1110 (
b1110 +
b1110 .
b1110 1
