assignment-05/custom-sequence-counter/design.v
/**
 * Task: count sequence 1, 32, 64, 128
 * Restriction: No behavioral code allowed. 
 */

//OK Tested
//map: 00 -> 1, 01 -> 32, 10 -> 64, 11 -> 128
module custom_decoder (
  input wire [1:0] state,
  output wire [7:0] decoded
);
  assign decoded[0] = ~state[1] & ~state[0];
  assign decoded[1] = state[1] & ~state[0];
  assign decoded[2] = state[1] & ~state[0];
  assign decoded[3] = state[1] & ~state[0];
  assign decoded[4] = state[1] & ~state[0];
  assign decoded[5] = state[1] ^ state[0];
  assign decoded[6] = 1'b0;
  assign decoded[7] = state[1] & state[0];
endmodule

module clock_gated_d_latch (
  input wire clk,    //high level sensitive
  input wire d,
  input wire rst,    //active-low asynchronus reset to 0
  output wire q
);
  wire t1, t2, t3, t4, t5, t6, t7;
  not (t1, d);
  and (t2, t1, clk);
  and (t3, d, clk);
  or (t5, t2, t4);
  not (t4, rst);
  and (t6, t3, rst);
  nor (q, t5, t7);
  nor (t7, q, t6);
endmodule

//OK Tested
module d_ff (
  input wire clk,    //+ve edge triggered
  input wire d,
  input wire rst,    //active-low asynchronus reset to 0
  output wire q
);
  wire t, neg_clk;
  assign neg_clk = ~clk;
  clock_gated_d_latch u1(.clk(neg_clk), .d(d), .rst(rst), .q(t));
  clock_gated_d_latch u2(.clk(clk), .d(t), .rst(rst), .q(q));
endmodule

module custom_sequence_counter (
  input wire clk,    //+ve edge triggered
  input wire rst,    //active-low reset
  output wire [7:0] count
);
  wire [1:0] state;
  custom_decoder u(.state(state), .decoded(count));
  wire t0, t1;
  assign t0 = ~state[0];
  assign t1 = state[0] ^ state[1]; 
  d_ff f0(.clk(clk), .d(t0), .rst(rst), .q(state[0]));
  d_ff f1(.clk(clk), .d(t1), .rst(rst), .q(state[1]));
endmodule

assignment-05/custom-sequence-counter/dff_tb.v
`timescale 1ns/100ps

module d_ff_tb;
  reg d, clk, rst;
  wire q;

  d_ff dut(.clk(clk), .rst(rst), .d(d), .q(q));

  initial begin
    $dumpfile("dff.vcd");
    $dumpvars(0, d_ff_tb);
    clk = 1'b0;
    rst = 1'b0;
    forever
      #5 clk = ~clk;
  end

  initial begin
    #2;
    rst = 1'b1; //released
    d = 0; #10;
    d = 1; #10;
    d = 0; #10;
    d = 1; #10;

    $finish;
  end
endmodule

assignment-05/custom-sequence-counter/dff.vcd
$date
	Fri Jun 26 13:34:32 2026
$end
$version
	Icarus Verilog
$end
$timescale
	100ps
$end
$scope module d_ff_tb $end
$var wire 1 ! q $end
$var reg 1 " clk $end
$var reg 1 # d $end
$var reg 1 $ rst $end
$scope module dut $end
$var wire 1 " clk $end
$var wire 1 # d $end
$var wire 1 % neg_clk $end
$var wire 1 $ rst $end
$var wire 1 & t $end
$var wire 1 ! q $end
$scope module u1 $end
$var wire 1 % clk $end
$var wire 1 # d $end
$var wire 1 & q $end
$var wire 1 $ rst $end
$var wire 1 ' t1 $end
$var wire 1 ( t2 $end
$var wire 1 ) t3 $end
$var wire 1 * t4 $end
$var wire 1 + t5 $end
$var wire 1 , t6 $end
$var wire 1 - t7 $end
$upscope $end
$scope module u2 $end
$var wire 1 " clk $end
$var wire 1 & d $end
$var wire 1 ! q $end
$var wire 1 $ rst $end
$var wire 1 . t1 $end
$var wire 1 / t2 $end
$var wire 1 0 t3 $end
$var wire 1 1 t4 $end
$var wire 1 2 t5 $end
$var wire 1 3 t6 $end
$var wire 1 4 t7 $end
$upscope $end
$upscope $end
$upscope $end
$enddefinitions $end
$comment Show the parameter values. $end
$dumpall
$end
#0
$dumpvars
14
03
12
11
00
0/
1.
1-
0,
1+
1*
x)
x(
x'
0&
1%
0$
x#
0"
0!
$end
#20
1.
0&
1(
1+
1-
02
1'
0)
0*
0,
01
0#
1$
#50
0+
0(
12
0%
1/
1"
#100
1+
1(
02
1%
0/
0"
#120
0.
1&
0+
0-
0(
1,
0'
1)
1#
#150
1!
0,
04
0)
13
0%
10
1"
#200
1,
1)
03
1%
00
0"
#220
1-
1.
0&
1+
1(
0,
1'
0)
0#
#250
14
0+
0!
0(
12
0%
1/
1"
#300
1+
1(
02
1%
0/
0"
#320
0.
1&
0+
0-
0(
1,
0'
1)
1#
#350
1!
0,
04
0)
13
0%
10
1"
#400
1,
1)
03
1%
00
0"
