assignment-05/custom-sequence-counter/design.v
/**
 * Task: count sequence 1, 32, 64, 128
 * Restriction: No behavioral code allowed. 
 */

//OK Tested
//map: 00 -> 1, 01 -> 32, 10 -> 64, 11 -> 128
module custom_decoder (
  input wire [1:0] state,
  output wire [7:0] decoded
);
  assign decoded[0] = ~state[1] & ~state[0];
  assign decoded[1] = state[1] & ~state[0];
  assign decoded[2] = state[1] & ~state[0];
  assign decoded[3] = state[1] & ~state[0];
  assign decoded[4] = state[1] & ~state[0];
  assign decoded[5] = state[1] ^ state[0];
  assign decoded[6] = 1'b0;
  assign decoded[7] = state[1] & state[0];
endmodule

module clock_gated_d_latch (
  input wire clk,    //high level sensitive
  input wire d,
  input wire rst,    //active-low asynchronus reset to 0
  output wire q
);
  wire t1, t2, t3, t4, t5, t6, t7;
  not (t1, d);
  and (t2, t1, clk);
  and (t3, d, clk);
  or (t5, t2, t4);
  not (t4, rst);
  and (t6, t3, rst);
  nor (q, t5, t7);
  nor (t7, q, t6);
endmodule

//OK Tested
module d_ff (
  input wire clk,    //+ve edge triggered
  input wire d,
  input wire rst,    //active-low asynchronus reset to 0
  output wire q
);
  wire t, neg_clk;
  assign neg_clk = ~clk;
  clock_gated_d_latch u1(.clk(neg_clk), .d(d), .rst(rst), .q(t));
  clock_gated_d_latch u2(.clk(clk), .d(t), .rst(rst), .q(q));
endmodule

module custom_sequence_counter (
  input wire clk,    //+ve edge triggered
  input wire rst,    //active-low reset
  output wire [7:0] count
);
  wire [1:0] state;
  custom_decoder u(.state(state), .decoded(count));
  wire t0, t1;
  assign t0 = ~state[0];
  assign t1 = state[0] ^ state[1]; 
  d_ff f0(.clk(clk), .d(t0), .rst(rst), .q(state[0]));
  d_ff f1(.clk(clk), .d(t1), .rst(rst), .q(state[1]));
endmodule

assignment-05/custom-sequence-counter/tb.v
`timescale 1ns/100ps

module custom_sequence_counter_tb;
  wire [7:0] count;
  wire [1:0] s;
  reg clk, rst;
  
  custom_sequence_counter dut(.clk(clk), .rst(rst), .count(count));

  initial begin
    $dumpfile("traces.vcd");
    $dumpvars(0, custom_sequence_counter_tb);
    clk = 1'b0;
    forever
      #5 clk = ~clk;
  end
  
  initial begin
    rst = 1'b0;
    #1;
    rst = 1'b1;
    
    for (integer i = 0; i < 10; i = i + 1) begin
      $display("#%3d  >> count = %3d", $time, count);
      #10;
    end

    $finish;
  end

endmodule

assignment-05/custom-sequence-counter/traces.vcd
$date
	Fri Jun 26 14:24:22 2026
$end
$version
	Icarus Verilog
$end
$timescale
	100ps
$end
$scope module custom_sequence_counter_tb $end
$var wire 8 ! count [7:0] $end
$var reg 1 " clk $end
$var reg 1 # rst $end
$scope module dut $end
$var wire 1 " clk $end
$var wire 1 # rst $end
$var wire 1 $ t0 $end
$var wire 1 % t1 $end
$var wire 2 & state [1:0] $end
$var wire 8 ' count [7:0] $end
$scope module f0 $end
$var wire 1 " clk $end
$var wire 1 $ d $end
$var wire 1 ( neg_clk $end
$var wire 1 # rst $end
$var wire 1 ) t $end
$var wire 1 * q $end
$scope module u1 $end
$var wire 1 ( clk $end
$var wire 1 $ d $end
$var wire 1 ) q $end
$var wire 1 # rst $end
$var wire 1 + t1 $end
$var wire 1 , t2 $end
$var wire 1 - t3 $end
$var wire 1 . t4 $end
$var wire 1 / t5 $end
$var wire 1 0 t6 $end
$var wire 1 1 t7 $end
$upscope $end
$scope module u2 $end
$var wire 1 " clk $end
$var wire 1 ) d $end
$var wire 1 * q $end
$var wire 1 # rst $end
$var wire 1 2 t1 $end
$var wire 1 3 t2 $end
$var wire 1 4 t3 $end
$var wire 1 5 t4 $end
$var wire 1 6 t5 $end
$var wire 1 7 t6 $end
$var wire 1 8 t7 $end
$upscope $end
$upscope $end
$scope module f1 $end
$var wire 1 " clk $end
$var wire 1 % d $end
$var wire 1 9 neg_clk $end
$var wire 1 # rst $end
$var wire 1 : t $end
$var wire 1 ; q $end
$scope module u1 $end
$var wire 1 9 clk $end
$var wire 1 % d $end
$var wire 1 : q $end
$var wire 1 # rst $end
$var wire 1 < t1 $end
$var wire 1 = t2 $end
$var wire 1 > t3 $end
$var wire 1 ? t4 $end
$var wire 1 @ t5 $end
$var wire 1 A t6 $end
$var wire 1 B t7 $end
$upscope $end
$scope module u2 $end
$var wire 1 " clk $end
$var wire 1 : d $end
$var wire 1 ; q $end
$var wire 1 # rst $end
$var wire 1 C t1 $end
$var wire 1 D t2 $end
$var wire 1 E t3 $end
$var wire 1 F t4 $end
$var wire 1 G t5 $end
$var wire 1 H t6 $end
$var wire 1 I t7 $end
$upscope $end
$upscope $end
$scope module u $end
$var wire 2 J state [1:0] $end
$var wire 8 K decoded [7:0] $end
$upscope $end
$upscope $end
$scope begin $ivl_for_loop0 $end
$var integer 32 L i [31:0] $end
$upscope $end
$upscope $end
$enddefinitions $end
$comment Show the parameter values. $end
$dumpall
$end
#0
$dumpvars
bx L
b1 K
b0 J
1I
0H
1G
1F
0E
0D
1C
1B
0A
1@
1?
0>
1=
1<
0;
0:
19
18
07
16
15
04
03
12
11
00
1/
1.
1-
0,
0+
0*
0)
1(
b1 '
b0 &
0%
1$
0#
0"
b1 !
$end
#10
02
1)
0/
01
06
0G
0.
10
05
0?
0F
b0 L
1#
#50
b100000 !
b100000 '
b100000 K
0<
1+
1%
0$
b1 &
b1 J
1*
00
08
0@
0-
17
0=
1G
0(
14
09
1D
1"
#100
0C
11
12
1:
0)
0B
1/
1A
1,
07
1>
0G
1(
04
19
0D
0"
#110
b1 L
#150
b111110 !
b111110 '
b111110 K
0+
1$
18
b10 &
b10 J
1;
0/
0*
0A
0I
0,
16
0>
1H
0(
13
09
1E
1"
#200
02
1)
01
10
1A
1-
06
1>
0H
1(
03
19
0E
0"
#210
b10 L
#250
b10000000 !
b10000000 '
b10000000 K
1<
1+
0%
0$
b11 &
b11 J
1*
00
08
0A
0-
17
0>
1H
0(
14
09
1E
1"
#300
11
12
1B
1C
0)
0:
1/
1@
1,
07
1=
0H
1(
04
19
0E
0"
#310
b11 L
#350
b1 !
b1 '
b1 K
0+
1$
18
1I
b0 &
b0 J
0/
0*
0@
0;
0,
16
0=
1G
0(
13
09
1D
1"
#400
02
1)
01
10
1@
1-
06
1=
0G
1(
03
19
0D
0"
#410
b100 L
#450
b100000 !
b100000 '
b100000 K
0<
1+
1%
0$
b1 &
b1 J
1*
00
08
0@
0-
17
0=
1G
0(
14
09
1D
1"
#500
0C
11
12
1:
0)
0B
1/
1A
1,
07
1>
0G
1(
04
19
0D
0"
#510
b101 L
#550
b111110 !
b111110 '
b111110 K
0+
1$
18
b10 &
b10 J
1;
0/
0*
0A
0I
0,
16
0>
1H
0(
13
09
1E
1"
#600
02
1)
01
10
1A
1-
06
1>
0H
1(
03
19
0E
0"
#610
b110 L
#650
b10000000 !
b10000000 '
b10000000 K
1<
1+
0%
0$
b11 &
b11 J
1*
00
08
0A
0-
17
0>
1H
0(
14
09
1E
1"
#700
11
12
1B
1C
0)
0:
1/
1@
1,
07
1=
0H
1(
04
19
0E
0"
#710
b111 L
#750
b1 !
b1 '
b1 K
0+
1$
18
1I
b0 &
b0 J
0/
0*
0@
0;
0,
16
0=
1G
0(
13
09
1D
1"
#800
02
1)
01
10
1@
1-
06
1=
0G
1(
03
19
0D
0"
#810
b1000 L
#850
b100000 !
b100000 '
b100000 K
0<
1+
1%
0$
b1 &
b1 J
1*
00
08
0@
0-
17
0=
1G
0(
14
09
1D
1"
#900
0C
11
12
1:
0)
0B
1/
1A
1,
07
1>
0G
1(
04
19
0D
0"
#910
b1001 L
#950
b111110 !
b111110 '
b111110 K
0+
1$
18
b10 &
b10 J
1;
0/
0*
0A
0I
0,
16
0>
1H
0(
13
09
1E
1"
#1000
02
1)
01
10
1A
1-
06
1>
0H
1(
03
19
0E
0"
#1010
b1010 L
