assignment-01/three_bit_full_adder/three_bit_full_adder.v
// Dataflow Modeling
module three_bit_full_adder_df(
  output [2:0] Sum,
  output Cout,
  input [2:0] A, B,
  input Cin
);
  wire c1, c2;
  assign {c1, Sum[0]} = A[0] + B[0] + Cin;
  assign {c2, Sum[1]} = A[1] + B[1] + c1;
  assign {Cout, Sum[2]} = A[2] + B[2] + c2;
endmodule

// Behavioral modelling
module three_bit_full_adder_beh(
  output reg [2:0] Sum,
  output reg Cout,
  input [2:0] A, B,
  input Cin
);
  always @(*) begin
    {Cout, Sum} = A + B + Cin;
  end
endmodule


module FA(
  output S, C,
  input wire x, y, z
);
  assign S = x ^ y ^ z;
  assign C = (x & y) | (y & z) | (x & z);
endmodule

// Structural modelling
module three_bit_full_adder_st(
  output [2:0] Sum,
  output Cout,
  input [2:0] A, B,
  input Cin
);
  wire w1, w2;
  FA g1(.S(Sum[0]), .C(w1), .x(A[0]), .y(B[0]), .z(Cin));
  FA g2(.S(Sum[1]), .C(w2), .x(A[1]), .y(B[1]), .z(w1));
  FA g3(.S(Sum[2]), .C(Cout), .x(A[2]), .y(B[2]), .z(w2));
endmodule

assignment-01/three_bit_full_adder/three_bit_full_adder_tb.v
`timescale 1ns/1ps

module three_bit_full_adder;
  reg [2:0] A, B;
  reg Cin;
  wire [2:0] Sum_df, Sum_beh, Sum_st;
  wire Cout_df, Cout_beh, Cout_st;

  three_bit_full_adder_df g1(.A(A), .B(B), .Cin(Cin), .Sum(Sum_df), .Cout(Cout_df));
  three_bit_full_adder_beh g2(.A(A), .B(B), .Cin(Cin), .Sum(Sum_beh), .Cout(Cout_beh));
  three_bit_full_adder_st g3(.A(A), .B(B), .Cin(Cin), .Sum(Sum_st), .Cout(Cout_st));
  
  // integer file;
  initial begin
    $dumpfile("three_bit_full_adder.vcd");
    $dumpvars(0, three_bit_full_adder);
    // file = $fopen("./output.txt", "w");
    // $fmonitor(file, $time, "   A = %3b   B = %3b   Cin = %b   Sum_df = %3b   Sum_beh = %3d   Sum_st = %3d   Cout_df = %b   Cout_beh = %b   Cout_st = %b", A, B, Cin, Sum_df, Sum_beh, Sum_st, Cout_df, Cout_beh, Cout_st);
    
    // for (integer i = 0; i < 128; i = i + 1) begin
    //   {A, B, Cin} = i;
    //   #1;
    // end
    {A, B, Cin} = {3'b000, 3'b000, 1'b0};
    #1 {A, B, Cin} = {3'b100, 3'b011, 1'b0};
    #1 {A, B, Cin} = {3'b100, 3'b111, 1'b0};
    #1 {A, B, Cin} = {3'b011, 3'b100, 1'b0};
    #1 {A, B, Cin} = {3'b111, 3'b000, 1'b0};
    #1 {A, B, Cin} = {3'b111, 3'b001, 1'b0};
    #1 {A, B, Cin} = {3'b111, 3'b000, 1'b1};
    #1 {A, B, Cin} = {3'b110, 3'b001, 1'b1};
    #1 {A, B, Cin} = {3'b100, 3'b011, 1'b1};
    #1 {A, B, Cin} = {3'b001, 3'b101, 1'b1};
    #1 {A, B, Cin} = {3'b101, 3'b010, 1'b1};
    #1 {A, B, Cin} = {3'b000, 3'b100, 1'b1};
    #1 {A, B, Cin} = {3'b100, 3'b000, 1'b1};
    #1 $finish;
  end
endmodule

assignment-01/three_bit_full_adder/three_bit_full_adder.vcd
$date
	Wed May 27 03:35:19 2026
$end
$version
	Icarus Verilog
$end
$timescale
	1ps
$end
$scope module three_bit_full_adder $end
$var wire 3 ! Sum_st [2:0] $end
$var wire 3 " Sum_df [2:0] $end
$var wire 3 # Sum_beh [2:0] $end
$var wire 1 $ Cout_st $end
$var wire 1 % Cout_df $end
$var wire 1 & Cout_beh $end
$var reg 3 ' A [2:0] $end
$var reg 3 ( B [2:0] $end
$var reg 1 ) Cin $end
$scope module g1 $end
$var wire 3 * A [2:0] $end
$var wire 3 + B [2:0] $end
$var wire 1 ) Cin $end
$var wire 1 , c2 $end
$var wire 1 - c1 $end
$var wire 3 . Sum [2:0] $end
$var wire 1 % Cout $end
$upscope $end
$scope module g2 $end
$var wire 3 / A [2:0] $end
$var wire 3 0 B [2:0] $end
$var wire 1 ) Cin $end
$var reg 1 & Cout $end
$var reg 3 1 Sum [2:0] $end
$upscope $end
$scope module g3 $end
$var wire 3 2 A [2:0] $end
$var wire 3 3 B [2:0] $end
$var wire 1 ) Cin $end
$var wire 1 4 w2 $end
$var wire 1 5 w1 $end
$var wire 3 6 Sum [2:0] $end
$var wire 1 $ Cout $end
$scope module g1 $end
$var wire 1 5 C $end
$var wire 1 7 S $end
$var wire 1 8 x $end
$var wire 1 9 y $end
$var wire 1 ) z $end
$upscope $end
$scope module g2 $end
$var wire 1 4 C $end
$var wire 1 : S $end
$var wire 1 ; x $end
$var wire 1 < y $end
$var wire 1 5 z $end
$upscope $end
$scope module g3 $end
$var wire 1 $ C $end
$var wire 1 = S $end
$var wire 1 > x $end
$var wire 1 ? y $end
$var wire 1 4 z $end
$upscope $end
$upscope $end
$upscope $end
$enddefinitions $end
$comment Show the parameter values. $end
$dumpall
$end
#0
$dumpvars
0?
0>
0=
0<
0;
0:
09
08
07
b0 6
05
04
b0 3
b0 2
b0 1
b0 0
b0 /
b0 .
0-
0,
b0 +
b0 *
0)
b0 (
b0 '
0&
0%
0$
b0 #
b0 "
b0 !
$end
#1000
b111 "
b111 .
b111 !
b111 6
1=
17
1:
1>
b111 #
b111 1
19
1<
b100 '
b100 *
b100 /
b100 2
b11 (
b11 +
b11 0
b11 3
#2000
b11 "
b11 .
b11 !
b11 6
1$
1%
0=
1&
b11 #
b11 1
1?
b111 (
b111 +
b111 0
b111 3
#3000
b111 "
b111 .
b111 !
b111 6
0$
0%
1=
18
1;
0>
0&
b111 #
b111 1
09
0<
b11 '
b11 *
b11 /
b11 2
b100 (
b100 +
b100 0
b100 3
#4000
1>
0?
b111 '
b111 *
b111 /
b111 2
b0 (
b0 +
b0 0
b0 3
#5000
1$
1%
0=
14
1,
0:
b0 "
b0 .
b0 !
b0 6
15
1-
07
1&
b0 #
b0 1
19
b1 (
b1 +
b1 0
b1 3
#6000
b0 "
b0 .
b0 !
b0 6
09
07
b0 (
b0 +
b0 0
b0 3
1)
#7000
08
19
b110 '
b110 *
b110 /
b110 2
b1 (
b1 +
b1 0
b1 3
#8000
0;
1<
b100 '
b100 *
b100 /
b100 2
b11 (
b11 +
b11 0
b11 3
#9000
0$
0%
1=
b111 "
b111 .
b111 !
b111 6
04
17
0,
1:
18
0>
0&
b111 #
b111 1
0<
1?
b1 '
b1 *
b1 /
b1 2
b101 (
b101 +
b101 0
b101 3
#10000
1$
1%
0=
b0 "
b0 .
b0 !
b0 6
14
1,
07
0:
1>
1&
b0 #
b0 1
09
1<
0?
b101 '
b101 *
b101 /
b101 2
b10 (
b10 +
b10 0
b10 3
#11000
0$
0%
1=
b101 "
b101 .
b101 !
b101 6
04
0-
17
05
0,
0:
08
0>
0&
b101 #
b101 1
0<
1?
b0 '
b0 *
b0 /
b0 2
b100 (
b100 +
b100 0
b100 3
#12000
1>
0?
b100 '
b100 *
b100 /
b100 2
b0 (
b0 +
b0 0
b0 3
