assignment-02/bcd_encoder/bcd_encoder.v
module bcd_encoder (
  output wire [4:0] out,  
  input wire [4:0] in //19 can be represented in 5 bits
);
  assign out[3:0] = in % 10;
  assign out[4] = (in > 9)? 1 : 0;
endmodule

assignment-02/bcd_encoder/bcd_encoder_tb.v
`timescale 1ns/1ps

module bcd_encoder_tb;
  reg [4:0] in;
  wire [4:0] out;
  bcd_encoder u1(.out(out), .in(in));
  
  initial begin
    $dumpfile("bcd_encoder.vcd");
    $dumpvars(0, bcd_encoder_tb);

    #0 in = 0;
    #1 in = 5;
    #1 in = 3;
    #1 in = 7;
    #1 in = 9;
    #1 in = 10;
    #1 in = 13;
    #1 in = 16;
    #1 in = 19;
    #1 in = 11;
    #1 $finish;
  end
endmodule

assignment-02/bcd_encoder/bcd_encoder.vcd
$date
	Mon Jun 08 03:33:44 2026
$end
$version
	Icarus Verilog
$end
$timescale
	1ps
$end
$scope module bcd_encoder_tb $end
$var wire 5 ! out [4:0] $end
$var reg 5 " in [4:0] $end
$scope module u1 $end
$var wire 5 # in [4:0] $end
$var wire 5 $ out [4:0] $end
$upscope $end
$upscope $end
$enddefinitions $end
$comment Show the parameter values. $end
$dumpall
$end
#0
$dumpvars
b0 $
b0 #
b0 "
b0 !
$end
#1000
b101 !
b101 $
b101 "
b101 #
#2000
b11 !
b11 $
b11 "
b11 #
#3000
b111 !
b111 $
b111 "
b111 #
#4000
b1001 !
b1001 $
b1001 "
b1001 #
#5000
b10000 !
b10000 $
b1010 "
b1010 #
#6000
b10011 !
b10011 $
b1101 "
b1101 #
#7000
b10110 !
b10110 $
b10000 "
b10000 #
#8000
b11001 !
b11001 $
b10011 "
b10011 #
#9000
b10001 !
b10001 $
b1011 "
b1011 #
