assignment-06/fsm-more-than-1s-in-last-three-samples/design.v
module fsm (
  input rst,     //active-low asynchronous reset
  input clk,     //+ve edge trigerred
  input x,
  output reg y
);
  reg [1:0] q;   //internal state
  always @(posedge clk or negedge rst) begin
    if (!rst) begin
      q <= 2'b00;
      y <= 0;
    end
    else begin
      q[0] <= x;
      q[1] <= q[0];
      y <= (q[1] & x) | (q[0] & x) | (&q);
    end
  end
endmodule

assignment-06/fsm-more-than-1s-in-last-three-samples/tb.v
`timescale 1ns/100ps

module tb;
  reg rst, clk, x;
  wire y;
  reg [0:9] seq_in, out_actual, out_expected;
  
  fsm dut(.rst(rst), .clk(clk), .x(x), .y(y));

  initial begin
    $dumpfile("traces.vcd");
    $dumpvars(0, tb);
    clk = 1'b0;
    forever
      #5 clk = ~clk;
  end

  initial begin
    rst = 1'b0;
    seq_in = 10'b0101011001;
    out_expected = 10'b0001011100;
    #3;
    
    rst = 1'b1;
    for (integer i = 0; i < 10; i = i + 1) begin
      x = seq_in[i]; #5;
      out_actual[i] = y; #5;
    end

    $display("seq_in      :  %b", seq_in);
    $display("out_actual  :  %b", out_actual);
    $display("out_expected:  %b", out_expected);

    #5 $finish;
  end

endmodule

assignment-06/fsm-more-than-1s-in-last-three-samples/traces.vcd
$date
	Mon Jul 06 20:04:56 2026
$end
$version
	Icarus Verilog
$end
$timescale
	100ps
$end
$scope module tb $end
$var wire 1 ! y $end
$var reg 1 " clk $end
$var reg 10 # out_actual [0:9] $end
$var reg 10 $ out_expected [0:9] $end
$var reg 1 % rst $end
$var reg 10 & seq_in [0:9] $end
$var reg 1 ' x $end
$scope module dut $end
$var wire 1 " clk $end
$var wire 1 % rst $end
$var wire 1 ' x $end
$var reg 2 ( q [1:0] $end
$var reg 1 ! y $end
$upscope $end
$scope begin $ivl_for_loop0 $end
$var integer 32 ) i [31:0] $end
$upscope $end
$upscope $end
$enddefinitions $end
$comment Show the parameter values. $end
$dumpall
$end
#0
$dumpvars
bx )
b0 (
x'
b101011001 &
0%
b1011100 $
bx #
0"
0!
$end
#30
0'
b0 )
1%
#50
1"
#80
b0xxxxxxxxx #
#100
0"
#130
1'
b1 )
#150
b1 (
1"
#180
b0xxxxxxxx #
#200
0"
#230
0'
b10 )
#250
b10 (
1"
#280
b0xxxxxxx #
#300
0"
#330
1'
b11 )
#350
1!
b1 (
1"
#380
b1xxxxxx #
#400
0"
#430
0'
b100 )
#450
0!
b10 (
1"
#480
b10xxxxx #
#500
0"
#530
1'
b101 )
#550
1!
b1 (
1"
#580
b101xxxx #
#600
0"
#630
b110 )
#650
b11 (
1"
#680
b1011xxx #
#700
0"
#730
0'
b111 )
#750
b10 (
1"
#780
b10111xx #
#800
0"
#830
b1000 )
#850
0!
b0 (
1"
#880
b101110x #
#900
0"
#930
1'
b1001 )
#950
b1 (
1"
#980
b1011100 #
#1000
0"
#1030
b1010 )
#1050
1!
b11 (
1"
