assignment-03/mux16x1/mux16x1.v
module mux16x1 (
  output reg out,
  input [15:0] in,
  input [3:0] sel
);
  always @(in, sel) rewire();

  task rewire ();
    begin
      out = in[sel];
    end
  endtask
endmodule

assignment-03/mux16x1/mux16x1_tb.v
`timescale 1ns/1ps

module mux16x1_tb;
  reg [15:0] in;
  reg [3:0] sel;
  wire out;
  
  mux16x1 u1(.out(out), .in(in), .sel(sel));
  
  initial begin
    $dumpfile("mux16x1.vcd");
    $dumpvars(0, mux16x1_tb);

    in = 16'b1100_1100_1010_1111;
    for (integer i = 0; i < 16; i = i + 1) begin
      sel = i; #1;
    end
    
    $finish;
  end
endmodule

assignment-03/mux16x1/mux16x1.vcd
$date
	Sat Jun 13 18:47:07 2026
$end
$version
	Icarus Verilog
$end
$timescale
	1ps
$end
$scope module mux16x1_tb $end
$var wire 1 ! out $end
$var reg 16 " in [15:0] $end
$var reg 4 # sel [3:0] $end
$scope module u1 $end
$var wire 16 $ in [15:0] $end
$var wire 4 % sel [3:0] $end
$var reg 1 ! out $end
$scope task rewire $end
$upscope $end
$upscope $end
$scope begin $ivl_for_loop0 $end
$var integer 32 & i [31:0] $end
$upscope $end
$upscope $end
$enddefinitions $end
$comment Show the parameter values. $end
$dumpall
$end
#0
$dumpvars
b0 &
b0 %
b1100110010101111 $
b0 #
b1100110010101111 "
1!
$end
#1000
b1 #
b1 %
b1 &
#2000
b10 #
b10 %
b10 &
#3000
b11 #
b11 %
b11 &
#4000
0!
b100 #
b100 %
b100 &
#5000
1!
b101 #
b101 %
b101 &
#6000
0!
b110 #
b110 %
b110 &
#7000
1!
b111 #
b111 %
b111 &
#8000
0!
b1000 #
b1000 %
b1000 &
#9000
b1001 #
b1001 %
b1001 &
#10000
1!
b1010 #
b1010 %
b1010 &
#11000
b1011 #
b1011 %
b1011 &
#12000
0!
b1100 #
b1100 %
b1100 &
#13000
b1101 #
b1101 %
b1101 &
#14000
1!
b1110 #
b1110 %
b1110 &
#15000
b1111 #
b1111 %
b1111 &
#16000
b10000 &
