assignment-05/switch-tail-counter/design.v
module switch_tail_counter #(
  parameter N = 8  //no. of bits to use
) (
  output reg [N-1:0] value,
  input clk,       //clock pulse
  input reset      //active-low
);
  always @(posedge clk or negedge reset) begin
    if (!reset) begin
      value = {(N-1){1'b0}};
    end
    else begin
      value <= value << 1;
      value[0] <= ~value[N-1];
    end
  end
endmodule

assignment-05/switch-tail-counter/tb.v
`timescale 1ns/100ps

module switch_tail_counter_tb;
  reg clk, reset;
  wire [3:0] value;

  switch_tail_counter#(4) u(.clk(clk), .reset(reset), .value(value));
  
  initial begin
    //clock generation
    clk = 1'b0;
    forever #1 clk = ~clk; //500MHz
  end

  initial begin
    $dumpfile("waveforms.vcd");
    $dumpvars(0, switch_tail_counter_tb);
    reset = 1'b0;
    #1.5 reset = 1'b1;
    #32 $finish;
  end
endmodule

assignment-05/switch-tail-counter/waveforms.vcd
$date
	Tue Jun 23 12:03:12 2026
$end
$version
	Icarus Verilog
$end
$timescale
	100ps
$end
$scope module switch_tail_counter_tb $end
$var wire 4 ! value [3:0] $end
$var reg 1 " clk $end
$var reg 1 # reset $end
$scope module u $end
$var wire 1 " clk $end
$var wire 1 # reset $end
$var parameter 32 $ N $end
$var reg 4 % value [3:0] $end
$upscope $end
$upscope $end
$enddefinitions $end
$comment Show the parameter values. $end
$dumpall
b100 $
$end
#0
$dumpvars
b0 %
0#
0"
b0 !
$end
#10
1"
#15
1#
#20
0"
#30
b1 !
b1 %
1"
#40
0"
#50
b11 !
b11 %
1"
#60
0"
#70
b111 !
b111 %
1"
#80
0"
#90
b1111 !
b1111 %
1"
#100
0"
#110
b1110 !
b1110 %
1"
#120
0"
#130
b1100 !
b1100 %
1"
#140
0"
#150
b1000 !
b1000 %
1"
#160
0"
#170
b0 !
b0 %
1"
#180
0"
#190
b1 !
b1 %
1"
#200
0"
#210
b11 !
b11 %
1"
#220
0"
#230
b111 !
b111 %
1"
#240
0"
#250
b1111 !
b1111 %
1"
#260
0"
#270
b1110 !
b1110 %
1"
#280
0"
#290
b1100 !
b1100 %
1"
#300
0"
#310
b1000 !
b1000 %
1"
#320
0"
#330
b0 !
b0 %
1"
