assignment-06/fsm-eliminate-short-length-pulses/design.v
module fsm (
  input rst,     //active-low asynchronous reset
  input clk,     //+ve edge trigerred
  input x,
  output reg y
);
  reg [2:0] q;   //internal state
  always @(posedge clk or negedge rst) begin
    if (!rst) begin
      q <= 3'b00;
      y <= 0;
    end
    else begin
      q[0] <= (~q[2] & x) | (~q[2] & ~q[1] & q[0]) | (q[0] & x);
      q[1] <= (~q[2] & ~q[1] & q[0] & ~x) | (q[2] & ~q[1] & ~q[0] & x);
      q[2] <= (q[1] & ~q[0]) | (q[2] & q[0]) | (~q[1] & q[0] & x);
      y <= (q[1] & ~q[0]) | (q[2] & x) | (q[2] & q[0]) | (~q[1] & q[0] & x);
    end
  end
endmodule

assignment-06/fsm-eliminate-short-length-pulses/tb.v
`timescale 1ns/100ps

module tb;
  reg rst, clk, x;
  wire y;
  reg [0:10] seq_in, out_actual, out_expected;
  
  fsm dut(.rst(rst), .clk(clk), .x(x), .y(y));

  initial begin
    $dumpfile("traces.vcd");
    $dumpvars(0, tb);
    clk = 1'b0;
    forever
      #5 clk = ~clk;
  end

  initial begin
    rst = 1'b0;
    seq_in       = 11'b01001101100;
    out_expected = 11'b00000111110;
    #3;
    
    rst = 1'b1;
    for (integer i = 0; i < 11; i = i + 1) begin
      x = seq_in[i]; #5;
      out_actual[i] = y; #5;
    end

    $display("seq_in      :  %b", seq_in);
    $display("out_actual  :  %b", out_actual);
    $display("out_expected:  %b", out_expected);

    #5 $finish;
  end

endmodule

assignment-06/fsm-eliminate-short-length-pulses/traces.vcd
$date
	Mon Jul 06 21:22:36 2026
$end
$version
	Icarus Verilog
$end
$timescale
	100ps
$end
$scope module tb $end
$var wire 1 ! y $end
$var reg 1 " clk $end
$var reg 11 # out_actual [0:10] $end
$var reg 11 $ out_expected [0:10] $end
$var reg 1 % rst $end
$var reg 11 & seq_in [0:10] $end
$var reg 1 ' x $end
$scope module dut $end
$var wire 1 " clk $end
$var wire 1 % rst $end
$var wire 1 ' x $end
$var reg 3 ( q [2:0] $end
$var reg 1 ! y $end
$upscope $end
$scope begin $ivl_for_loop0 $end
$var integer 32 ) i [31:0] $end
$upscope $end
$upscope $end
$enddefinitions $end
$comment Show the parameter values. $end
$dumpall
$end
#0
$dumpvars
bx )
b0 (
x'
b1001101100 &
0%
b111110 $
bx #
0"
0!
$end
#30
0'
b0 )
1%
#50
1"
#80
b0xxxxxxxxxx #
#100
0"
#130
1'
b1 )
#150
b1 (
1"
#180
b0xxxxxxxxx #
#200
0"
#230
0'
b10 )
#250
b11 (
1"
#280
b0xxxxxxxx #
#300
0"
#330
b11 )
#350
b0 (
1"
#380
b0xxxxxxx #
#400
0"
#430
1'
b100 )
#450
b1 (
1"
#480
b0xxxxxx #
#500
0"
#530
b101 )
#550
1!
b101 (
1"
#580
b1xxxxx #
#600
0"
#630
0'
b110 )
#650
b100 (
1"
#680
b11xxxx #
#700
0"
#730
1'
b111 )
#750
b10 (
1"
#780
b111xxx #
#800
0"
#830
b1000 )
#850
b101 (
1"
#880
b1111xx #
#900
0"
#930
0'
b1001 )
#950
b100 (
1"
#980
b11111x #
#1000
0"
#1030
b1010 )
#1050
0!
b0 (
1"
#1080
b111110 #
#1100
0"
#1130
b1011 )
