assignment-03/encoder8x3/encoder8x3.v
module encoder8x3 (
  output reg [2:0] out,
  input [7:0] in
);
  always @(in) rewire();

  task rewire;
    begin
      case (in)
        8'b0000_0001: out = 3'h0;
        8'b0000_0010: out = 3'h1;
        8'b0000_0100: out = 3'h2;
        8'b0000_1000: out = 3'h3;
        8'b0001_0000: out = 3'h4;
        8'b0010_0000: out = 3'h5;
        8'b0100_0000: out = 3'h6;
        8'b1000_0000: out = 3'h7;
        default:      out = 3'h0;
      endcase
    end
  endtask
endmodule

assignment-03/encoder8x3/encoder8x3_tb.v
`timescale 1ns/1ps

module encoder8x3_tb;
  reg [7:0] a;
  wire [2:0] y;
  
  encoder8x3 u1(.out(y), .in(a));

  initial begin
    $dumpfile("encoder8x3.vcd");
    $dumpvars(0, encoder8x3_tb);

    for (integer i = 1; i < 2 ** 8; i = i * 2) begin
      a = i; #1;
    end
    a = 8'b1000_0001; #1; //invalid
    a = 8'b0000_0000; #1; //invalid
    $finish;
  end
endmodule

assignment-03/encoder8x3/encoder8x3.vcd
$date
	Sat Jun 13 18:24:58 2026
$end
$version
	Icarus Verilog
$end
$timescale
	1ps
$end
$scope module encoder8x3_tb $end
$var wire 3 ! y [2:0] $end
$var reg 8 " a [7:0] $end
$scope module u1 $end
$var wire 8 # in [7:0] $end
$var reg 3 $ out [2:0] $end
$scope task rewire $end
$upscope $end
$upscope $end
$scope begin $ivl_for_loop0 $end
$var integer 32 % i [31:0] $end
$upscope $end
$upscope $end
$enddefinitions $end
$comment Show the parameter values. $end
$dumpall
$end
#0
$dumpvars
b1 %
b0 $
b1 #
b1 "
b0 !
$end
#1000
b1 !
b1 $
b10 "
b10 #
b10 %
#2000
b10 !
b10 $
b100 "
b100 #
b100 %
#3000
b11 !
b11 $
b1000 "
b1000 #
b1000 %
#4000
b100 !
b100 $
b10000 "
b10000 #
b10000 %
#5000
b101 !
b101 $
b100000 "
b100000 #
b100000 %
#6000
b110 !
b110 $
b1000000 "
b1000000 #
b1000000 %
#7000
b111 !
b111 $
b10000000 "
b10000000 #
b10000000 %
#8000
b0 !
b0 $
b10000001 "
b10000001 #
b100000000 %
#9000
b0 "
b0 #
