assignment-05/siso-register/design.v
module siso_register #(
  parameter N = 8
) (
  input wire clk,        //+ve edge triggered
  input wire rst,        //active-low reset to all 0's
  input wire en,         //allow to load
  input wire d_in,       //input data bit
  output wire d_out      //ouput data bit
);
  //data MSB first-in first-out
  reg [N-1:0] data;
  assign d_out = data[N-1];

  always @(posedge clk or negedge rst) begin
    if (!rst)
      data <= {N{1'b0}};
    else
      if (en)
        data <= {data[N-2:0], d_in};
  end
endmodule

assignment-05/siso-register/tb.v
`timescale 1ns/100ps

module siso_reg_tb;
  reg [7:0] data_in, data_out;
  
  reg clk, d_in, en, rst;
  wire d_out;
  
  siso_register#(8) dut(.clk(clk), .en(en), .rst(rst), .d_in(d_in), .d_out(d_out));

  initial begin
    $dumpfile("traces.vcd");
    $dumpvars(0, siso_reg_tb);
    data_in = 8'b10100101;   //data to be written
    data_out = 8'b0;
    clk = 1'b0;
    forever
      #5 clk = ~clk;         //100 MHz clock
  end
  
  always @(posedge clk)
    #1 $display("#%5d >>  en = %b  rst = %b  d_in = %b  d_out = %b  data_in = %8b  data_out = %8b", $time, en, rst, d_in, d_out, data_in, data_out);
      
  initial begin
    en = 1'b1;               //enable register for operations
    rst = 1'b0;              //reset register
    #1 rst = 1'b1;           //releasing register data transfers
    
    #3; //taking setup time 1 time unit
    for (integer i = 7; i > -1; i = i - 1) begin
      d_in = data_in[i]; #10;
    end

    en = 1'b0; #20;          //retaining data

    en = 1'b1;               //reading_data
    for (integer i = 0; i < 8; i = i + 1) begin
      data_out = {data_out[6:0], d_out}; #10;
    end

    #20 $finish;
  end
endmodule

assignment-05/siso-register/traces.vcd
$date
	Thu Jun 25 15:48:18 2026
$end
$version
	Icarus Verilog
$end
$timescale
	100ps
$end
$scope module siso_reg_tb $end
$var wire 1 ! d_out $end
$var reg 1 " clk $end
$var reg 1 # d_in $end
$var reg 8 $ data_in [7:0] $end
$var reg 8 % data_out [7:0] $end
$var reg 1 & en $end
$var reg 1 ' rst $end
$scope module dut $end
$var wire 1 " clk $end
$var wire 1 # d_in $end
$var wire 1 & en $end
$var wire 1 ' rst $end
$var wire 1 ! d_out $end
$var parameter 32 ( N $end
$var reg 8 ) data [7:0] $end
$upscope $end
$scope begin $ivl_for_loop0 $end
$var integer 32 * i [31:0] $end
$upscope $end
$scope begin $ivl_for_loop1 $end
$var integer 32 + i [31:0] $end
$upscope $end
$upscope $end
$enddefinitions $end
$comment Show the parameter values. $end
$dumpall
b1000 (
$end
#0
$dumpvars
bx +
bx *
b0 )
0'
1&
b0 %
b10100101 $
x#
0"
0!
$end
#10
1'
#40
1#
b111 *
#50
b1 )
1"
#100
0"
#140
0#
b110 *
#150
b10 )
1"
#200
0"
#240
1#
b101 *
#250
b101 )
1"
#300
0"
#340
0#
b100 *
#350
b1010 )
1"
#400
0"
#440
b11 *
#450
b10100 )
1"
#500
0"
#540
1#
b10 *
#550
b101001 )
1"
#600
0"
#640
0#
b1 *
#650
b1010010 )
1"
#700
0"
#740
1#
b0 *
#750
1!
b10100101 )
1"
#800
0"
#840
0&
b11111111111111111111111111111111 *
#850
1"
#900
0"
#950
1"
#1000
0"
#1040
b1 %
b0 +
1&
#1050
0!
b1001011 )
1"
#1100
0"
#1140
b10 %
b1 +
#1150
1!
b10010111 )
1"
#1200
0"
#1240
b101 %
b10 +
#1250
0!
b101111 )
1"
#1300
0"
#1340
b1010 %
b11 +
#1350
b1011111 )
1"
#1400
0"
#1440
b10100 %
b100 +
#1450
1!
b10111111 )
1"
#1500
0"
#1540
b101001 %
b101 +
#1550
0!
b1111111 )
1"
#1600
0"
#1640
b1010010 %
b110 +
#1650
1!
b11111111 )
1"
#1700
0"
#1740
b10100101 %
b111 +
#1750
1"
#1800
0"
#1840
b1000 +
