assignment-05/sipo-register/design.v
module sipo_register #(
  parameter N = 8
) (
  input wire clk,                //+ve edge triggered
  input wire rst,                //active-low reset to all 0's
  input wire en,                 //allow to load
  input wire d_in,               //input data bit
  output wire [N-1:0] d_out      //ouput data
);
  //data MSB first-in
  reg [N-1:0] data;
  assign d_out = data;

  always @(posedge clk or negedge rst) begin
    if (!rst)
      data <= {N{1'b0}};
    else
      if (en)
        data <= {data[N-2:0], d_in};
  end
endmodule

assignment-05/sipo-register/tb.v
`timescale 1ns/100ps

module sipo_reg_tb;
  reg [3:0] data_in;
  
  reg clk, d_in, en, rst;
  wire [3:0] d_out;
  
  sipo_register#(4) dut(.clk(clk), .en(en), .rst(rst), .d_in(d_in), .d_out(d_out));

  initial begin
    $dumpfile("traces.vcd");
    $dumpvars(0, sipo_reg_tb);
    data_in = 4'b1001;   //data to be written
    clk = 1'b0;
    forever
      #5 clk = ~clk;         //100 MHz clock
  end
  
  always @(posedge clk)
    #1 $display("#%5d >>  en = %b  rst = %b  d_in = %b  d_out = %4b  data_in = %4b", $time, en, rst, d_in, d_out, data_in);
      
  initial begin
    en = 1'b1;               //enable register for operations
    rst = 1'b0;              //reset register
    #1 rst = 1'b1;           //releasing register data transfers
    
    #3; //taking setup time 1 time unit
    for (integer i = 3; i > -1; i = i - 1) begin
      d_in = data_in[i]; #10;
    end

    en = 1'b0; #20;          //retaining data

    en = 1'b1;               //writing another data
    data_in = 4'b1110;
    for (integer i = 3; i > -1; i = i - 1) begin
      d_in = data_in[i]; #10;
    end
    en = 1'b0; #10;          //retaining data
    $finish;
  end
endmodule

assignment-05/sipo-register/traces.vcd
$date
	Thu Jun 25 19:24:07 2026
$end
$version
	Icarus Verilog
$end
$timescale
	100ps
$end
$scope module sipo_reg_tb $end
$var wire 4 ! d_out [3:0] $end
$var reg 1 " clk $end
$var reg 1 # d_in $end
$var reg 4 $ data_in [3:0] $end
$var reg 1 % en $end
$var reg 1 & rst $end
$scope module dut $end
$var wire 1 " clk $end
$var wire 1 # d_in $end
$var wire 4 ' d_out [3:0] $end
$var wire 1 % en $end
$var wire 1 & rst $end
$var parameter 32 ( N $end
$var reg 4 ) data [3:0] $end
$upscope $end
$scope begin $ivl_for_loop0 $end
$var integer 32 * i [31:0] $end
$upscope $end
$scope begin $ivl_for_loop1 $end
$var integer 32 + i [31:0] $end
$upscope $end
$upscope $end
$enddefinitions $end
$comment Show the parameter values. $end
$dumpall
b100 (
$end
#0
$dumpvars
bx +
bx *
b0 )
b0 '
0&
1%
b1001 $
x#
0"
b0 !
$end
#10
1&
#40
1#
b11 *
#50
b1 !
b1 '
b1 )
1"
#100
0"
#140
0#
b10 *
#150
b10 !
b10 '
b10 )
1"
#200
0"
#240
b1 *
#250
b100 !
b100 '
b100 )
1"
#300
0"
#340
1#
b0 *
#350
b1001 !
b1001 '
b1001 )
1"
#400
0"
#440
0%
b11111111111111111111111111111111 *
#450
1"
#500
0"
#550
1"
#600
0"
#640
b11 +
b1110 $
1%
#650
b11 !
b11 '
b11 )
1"
#700
0"
#740
b10 +
#750
b111 !
b111 '
b111 )
1"
#800
0"
#840
b1 +
#850
b1111 !
b1111 '
b1111 )
1"
#900
0"
#940
0#
b0 +
#950
b1110 !
b1110 '
b1110 )
1"
#1000
0"
#1040
0%
b11111111111111111111111111111111 +
