assignment-02/priority_encoders/priority_encoders.v
module priority_encoder4x2 (
  output reg [1:0] out,
  input wire [3:0] in,
  input wire en
);
  always @(*) begin
    if (en === 1) begin
      casez (in)
        4'b1???: out = 3;
        4'b01??: out = 2;
        4'b001?: out = 1;
        4'b0001: out = 0;
        default: out = 0;
      endcase
    end
    else
      out = 0;
  end
endmodule

module priority_encoder8x3 (
  output reg [2:0] out,
  input wire [7:0] in,
  input wire en
);
  always @(*) begin
    if (en === 1) begin
      casez (in)
        8'b1???_????: out = 7;
        8'b01??_????: out = 6;
        8'b001?_????: out = 5;
        8'b0001_????: out = 4;
        8'b0000_1???: out = 3;
        8'b0000_01??: out = 2;
        8'b0000_001?: out = 1;
        8'b0000_0001: out = 0;
        default: out = 0;
      endcase
    end
    else
      out = 0;
  end
endmodule

assignment-02/priority_encoders/priority_encoders_tb.v
`timescale 1ns/1ps

module priority_encoders_tb;
  reg [3:0] I1;
  reg E1;
  wire [1:0] Y1;
  priority_encoder4x2 u1(.out(Y1), .in(I1), .en(E1));

  reg [7:0] I2;
  reg E2;
  wire [2:0] Y2;
  priority_encoder8x3 u2(.out(Y2), .in(I2), .en(E2));
  
  initial begin
    $dumpfile("priority_encoders.vcd");
    $dumpvars(0, priority_encoders_tb);
    #12 $finish;
  end

  initial begin
    E1 = 0;
    #1 E1 = 1;
    for (integer i = 0; i < 4; i = i + 1) begin
      I1 = 1 << i;
      #1;
    end
    I1 = 4'b1001; #1; // valid
    I1 = 4'b0011; #1; // valid
    E1 = 0;
  end
  
  initial begin
    E2 = 0;
    #1 E2 = 1;
    for (integer i = 0; i < 8; i = i + 1) begin
      I2 = 1 << i;
      #1;
    end
    I2 = 8'b1000_0001; #1; //valid
    I2 = 8'b0000_1001; #1; //valid
    E2 = 0;
  end
endmodule

assignment-02/priority_encoders/priority_encoders.vcd
$date
	Mon Jun 08 02:50:44 2026
$end
$version
	Icarus Verilog
$end
$timescale
	1ps
$end
$scope module priority_encoders_tb $end
$var wire 3 ! Y2 [2:0] $end
$var wire 2 " Y1 [1:0] $end
$var reg 1 # E1 $end
$var reg 1 $ E2 $end
$var reg 4 % I1 [3:0] $end
$var reg 8 & I2 [7:0] $end
$scope module u1 $end
$var wire 1 # en $end
$var wire 4 ' in [3:0] $end
$var reg 2 ( out [1:0] $end
$upscope $end
$scope module u2 $end
$var wire 1 $ en $end
$var wire 8 ) in [7:0] $end
$var reg 3 * out [2:0] $end
$upscope $end
$scope begin $ivl_for_loop0 $end
$var integer 32 + i [31:0] $end
$upscope $end
$scope begin $ivl_for_loop1 $end
$var integer 32 , i [31:0] $end
$upscope $end
$upscope $end
$enddefinitions $end
$comment Show the parameter values. $end
$dumpall
$end
#0
$dumpvars
bx ,
bx +
b0 *
bx )
b0 (
bx '
bx &
bx %
0$
0#
b0 "
b0 !
$end
#1000
b1 &
b1 )
b0 ,
1$
b1 %
b1 '
b0 +
1#
#2000
b1 !
b1 *
b1 "
b1 (
b10 &
b10 )
b1 ,
b10 %
b10 '
b1 +
#3000
b10 !
b10 *
b10 "
b10 (
b100 &
b100 )
b10 ,
b100 %
b100 '
b10 +
#4000
b11 !
b11 *
b11 "
b11 (
b1000 &
b1000 )
b11 ,
b1000 %
b1000 '
b11 +
#5000
b100 !
b100 *
b10000 &
b10000 )
b100 ,
b1001 %
b1001 '
b100 +
#6000
b101 !
b101 *
b1 "
b1 (
b100000 &
b100000 )
b101 ,
b11 %
b11 '
#7000
b110 !
b110 *
b0 "
b0 (
b1000000 &
b1000000 )
b110 ,
0#
#8000
b111 !
b111 *
b10000000 &
b10000000 )
b111 ,
#9000
b10000001 &
b10000001 )
b1000 ,
#10000
b11 !
b11 *
b1001 &
b1001 )
#11000
b0 !
b0 *
0$
