assignment-05/sync-up-down-counter/design.v
module sync_up_down_counter #(
  parameter N = 8  //no. of bits to use
) (
  output reg [N-1:0] value,
  input countDown, // if 1'b1 count down else up     
  input clk,       //clock pulse
  input reset      //active-low
);
  always @(posedge clk or negedge reset) begin
    if (!reset)
      value = {N{1'b0}};
    else begin
      if (countDown) begin
        value = (value == {N{1'b0}})? {N{1'b1}} : value - 1;
      end
      else begin
        value = (value == {N{1'b1}})? {N{1'b0}} : value + 1;
      end
    end
  end
endmodule

assignment-05/sync-up-down-counter/tb.v
`timescale 1ns/100ps

module sync_up_down_counter_tb;
  reg clk, countDown, reset;
  wire [1:0] value;

  sync_up_down_counter#(2) u(.clk(clk), .countDown(countDown), .reset(reset), .value(value));

  initial begin
    clk = 1'b0;
    forever #1 clk = ~clk;
  end

  initial begin
    $dumpfile("waveforms.vcd");
    $dumpvars(0, sync_up_down_counter_tb);
    reset = 1'b0;
    countDown = 1'b0; //count up
    #1.2 reset = 1'b1;
    #10 countDown = 1'b1;
    #10 countDown = 1'b0;

    #4 $finish;
  end
endmodule

assignment-05/sync-up-down-counter/waveforms.vcd
$date
	Tue Jun 23 12:22:52 2026
$end
$version
	Icarus Verilog
$end
$timescale
	100ps
$end
$scope module sync_up_down_counter_tb $end
$var wire 2 ! value [1:0] $end
$var reg 1 " clk $end
$var reg 1 # countDown $end
$var reg 1 $ reset $end
$scope module u $end
$var wire 1 " clk $end
$var wire 1 # countDown $end
$var wire 1 $ reset $end
$var parameter 32 % N $end
$var reg 2 & value [1:0] $end
$upscope $end
$upscope $end
$enddefinitions $end
$comment Show the parameter values. $end
$dumpall
b10 %
$end
#0
$dumpvars
b0 &
0$
0#
0"
b0 !
$end
#10
1"
#12
1$
#20
0"
#30
b1 !
b1 &
1"
#40
0"
#50
b10 !
b10 &
1"
#60
0"
#70
b11 !
b11 &
1"
#80
0"
#90
b0 !
b0 &
1"
#100
0"
#110
b1 !
b1 &
1"
#112
1#
#120
0"
#130
b0 !
b0 &
1"
#140
0"
#150
b11 !
b11 &
1"
#160
0"
#170
b10 !
b10 &
1"
#180
0"
#190
b1 !
b1 &
1"
#200
0"
#210
b0 !
b0 &
1"
#212
0#
#220
0"
#230
b1 !
b1 &
1"
#240
0"
#250
b10 !
b10 &
1"
