assignment-06/fsm-detect-101-in-last-4-samples/design.v
module fsm (
  input rst,     //active-low asynchronous reset
  input clk,     //+ve edge trigerred
  input x,
  output reg y
);
  reg [1:0] q;   //internal state
  always @(posedge clk or negedge rst) begin
    if (!rst) begin
      q <= 2'b00;
      y <= 0;
    end
    else begin
      q[0] <= x;
      q[1] <= (q[0] & ~x) | (q[1] & ~q[0] & x);
      y <= (q[1] & x) | (q[1] & q[0]);
    end
  end
endmodule

assignment-06/fsm-detect-101-in-last-4-samples/tb.v
`timescale 1ns/100ps

module tb;
  reg rst, clk, x;
  wire y;
  reg [0:12] seq_in, out_actual, out_expected;
  
  fsm dut(.rst(rst), .clk(clk), .x(x), .y(y));

  initial begin
    $dumpfile("traces.vcd");
    $dumpvars(0, tb);
    clk = 1'b0;
    forever
      #5 clk = ~clk;
  end

  initial begin
    rst = 1'b0;
    seq_in = 13'b0101001101010;
    out_expected = 13'b0001100001111;
    #3;
    
    rst = 1'b1;
    for (integer i = 0; i < 13; i = i + 1) begin
      x = seq_in[i]; #5;
      out_actual[i] = y; #5;
    end

    $display("seq_in      :  %b", seq_in);
    $display("out_actual  :  %b", out_actual);
    $display("out_expected:  %b", out_expected);

    #5 $finish;
  end

endmodule

assignment-06/fsm-detect-101-in-last-4-samples/traces.vcd
$date
	Tue Jul 07 11:50:13 2026
$end
$version
	Icarus Verilog
$end
$timescale
	100ps
$end
$scope module tb $end
$var wire 1 ! y $end
$var reg 1 " clk $end
$var reg 13 # out_actual [0:12] $end
$var reg 13 $ out_expected [0:12] $end
$var reg 1 % rst $end
$var reg 13 & seq_in [0:12] $end
$var reg 1 ' x $end
$scope module dut $end
$var wire 1 " clk $end
$var wire 1 % rst $end
$var wire 1 ' x $end
$var reg 2 ( q [1:0] $end
$var reg 1 ! y $end
$upscope $end
$scope begin $ivl_for_loop0 $end
$var integer 32 ) i [31:0] $end
$upscope $end
$upscope $end
$enddefinitions $end
$comment Show the parameter values. $end
$dumpall
$end
#0
$dumpvars
bx )
b0 (
x'
b101001101010 &
0%
b1100001111 $
bx #
0"
0!
$end
#30
0'
b0 )
1%
#50
1"
#80
b0xxxxxxxxxxxx #
#100
0"
#130
1'
b1 )
#150
b1 (
1"
#180
b0xxxxxxxxxxx #
#200
0"
#230
0'
b10 )
#250
b10 (
1"
#280
b0xxxxxxxxxx #
#300
0"
#330
1'
b11 )
#350
1!
b11 (
1"
#380
b1xxxxxxxxx #
#400
0"
#430
0'
b100 )
#450
b10 (
1"
#480
b11xxxxxxxx #
#500
0"
#530
b101 )
#550
0!
b0 (
1"
#580
b110xxxxxxx #
#600
0"
#630
1'
b110 )
#650
b1 (
1"
#680
b1100xxxxxx #
#700
0"
#730
b111 )
#750
1"
#780
b11000xxxxx #
#800
0"
#830
0'
b1000 )
#850
b10 (
1"
#880
b110000xxxx #
#900
0"
#930
1'
b1001 )
#950
1!
b11 (
1"
#980
b1100001xxx #
#1000
0"
#1030
0'
b1010 )
#1050
b10 (
1"
#1080
b11000011xx #
#1100
0"
#1130
1'
b1011 )
#1150
b11 (
1"
#1180
b110000111x #
#1200
0"
#1230
0'
b1100 )
#1250
b10 (
1"
#1280
b1100001111 #
#1300
0"
#1330
b1101 )
#1350
0!
b0 (
1"
